vnpy_mydata/__about__.py
vnpy_mydata/__init__.py
vnpy_mydata-0.0.1.dist-info/METADATA
vnpy_mydata-0.0.1.dist-info/WHEEL
vnpy_mydata-0.0.1.dist-info/licenses/LICENSE.txt
vnpy_mydata-0.0.1.dist-info/RECORD
