Metadata-Version: 2.3
Name: vnpy_mydata
Version: 0.0.1
Summary: vnpy_mydata
Project-URL: Documentation, https://github.com/unknown/vnpy_mydata#readme
Project-URL: Issues, https://github.com/unknown/vnpy_mydata/issues
Project-URL: Source, https://github.com/unknown/vnpy_mydata
Author-email: liuyanzhi08 <702368372@qq.com>
License-Expression: MIT
License-File: LICENSE.txt
Classifier: Development Status :: 4 - Beta
Classifier: Programming Language :: Python
Classifier: Programming Language :: Python :: 3.8
Classifier: Programming Language :: Python :: 3.9
Classifier: Programming Language :: Python :: 3.10
Classifier: Programming Language :: Python :: 3.11
Classifier: Programming Language :: Python :: 3.12
Classifier: Programming Language :: Python :: Implementation :: CPython
Classifier: Programming Language :: Python :: Implementation :: PyPy
Requires-Python: >=3.8
